NPTEL/Dff.v
module udpDff (output Q,input D,input Clk,input Rst);
  reg Q;
  always @(posedge Clk or posedge Rst)begin
    if (!Rst) begin
    	Q = D;  
    end
    else begin
      Q = 0;
    end
  end
endmodule

NPTEL/tb_Dff.v
module tb_Dff;  // change module name
    parameter clock_period = 5;
    parameter end_time = 100;
    reg D,Clk,Rst; wire Q;   // Declare all inputs to DUT as reg and output as wire
    udpDff dff(Q,D,Clk,Rst);  // instantiate DUT as <modulename> <instance-name>(size[wid:th])
    reg [1:0] R;
    initial
    begin
        $monitor ($time , " Q=%b, D=%d, Clk=%d, Rst=%b", // monitor
        Q, D, Clk, Rst);
        $dumpfile ("VCD/Dff.vcd"); // VCD file name
		$dumpvars (0, tb_Dff );  // Dumpvars to test waveform
        // En =1'b1;
        //En =1'b1;
        // #clock_period $display("started");  // phase shift of clock by half cycle

        // #clock_period D = 1'b1;  Rst = 1'b1;
        // //En =1'b0;
        // #clock_period D = 1'b1;  Rst = 1'b1;
        // //En =1'b1;
        // #clock_period D = 1'b1;  Rst = 1'b0;
        // //En =1'b0;
        // #clock_period D = 1'b1;  Rst = 1'b0;
        //En =1'b1;
    end

    always @(negedge Clk) begin

        #2 R = $random %2;
        D = R[0];
        Rst = R[1]; 
    end
    initial Clk = 1'b0;

    always #clock_period Clk = ~Clk;

    initial #end_time $finish;
endmodule

VCD/Dff.vcd
$date
	Tue Aug 30 22:47:52 2022
$end
$version
	Icarus Verilog
$end
$timescale
	1s
$end
$scope module tb_Dff $end
$var wire 1 ! Q $end
$var reg 1 " Clk $end
$var reg 1 # D $end
$var reg 2 $ R [1:0] $end
$var reg 1 % Rst $end
$scope module dff $end
$var wire 1 " Clk $end
$var wire 1 # D $end
$var wire 1 % Rst $end
$var reg 1 ! Q $end
$upscope $end
$upscope $end
$enddefinitions $end
#0
$dumpvars
x%
bx $
x#
0"
x!
$end
#2
0%
0#
b0 $
#5
0!
1"
#10
0"
#12
1%
1#
b11 $
#15
1"
#20
0"
#25
1"
#30
0"
#35
1"
#40
0"
#42
0%
b1 $
#45
1!
1"
#50
0"
#55
1"
#60
0"
#62
0!
1%
b11 $
#65
1"
#70
0"
#72
0%
0#
b0 $
#75
1"
#80
0"
#82
1#
b1 $
#85
1!
1"
