NPTEL/seq_detect_mealy.v
module seq_detect_mealy
  (
    output reg y,   // output y, single bit
    input x,    // input x, single bit
    input clk,  // input clock signal
    input clr   // input clear, active low
  );

  parameter S0 = 0, S1 = 1, S2 = 2;  // FSM has 3 states
  reg [1:0] state, next_state; // To store 3 states, we need a 2 bit register called state

  always @(clr) begin
    if(clr==0) begin
      state = S0;
      next_state = S0;
    end
  end

  always @(posedge clk) begin // state change procedural block 
      // y = y_prev;
      state = next_state;
  end
  
  always @(x,state) begin  // State transition function T: State x Input_symbol -> State
    case (state)
      S0: begin
        if (x == 1'b0) next_state = S1;
        else if (x == 1'b1) next_state = S2;
        else next_state = S0;
      end
      
      S1: begin
        if (x == 1'b0) next_state = S1;
        else if (x == 1'b1) next_state = S2;
        else next_state = S1;
      end
      
      S2: begin
        if (x == 1'b0) next_state = S1;
        else if (x == 1'b1) next_state = S2;
        else next_state = S2;
      end
      
      default: begin
        state = S0;
        next_state = S0;
      end
    endcase
  end
  
  //In case of Mealy machine, an output is associated with a state transition
  always @(x,state) begin // Output function G: State -> Output Symbol, here 0 or 1
    case (state)
      S0: begin
        if(x == 0) y = 0;
        else y = 0;
      end

      S1: begin
        if(x==0) y = 1;
        else y = 0;
      end
  
      S2: begin
        if(x==0) y = 1;
        else y = 0;
      end
    endcase
  end
endmodule

NPTEL/tb_seq_detect.v
module tb_seq_detect;
    wire y;
    reg x,clk,clr;
    seq_detect_mealy sq(y,x,clk,clr);
    wire state, next_state;
    assign state = sq.state;
    assign next_state = sq.next_state;
    initial begin 
      clr = 0; clk = 0;
      #5 clr = 1;
      #50 $finish;
    end
    
    initial begin
    $dumpfile ("VCD/seq_detect_mealey.vcd"); // VCD file name
		$dumpvars (0, tb_seq_detect );  // Dumpvars to test waveform
    $monitor($time," clk = %b x = %b y = %b state = %d next_state = %d, clr = %b", clk, x, y, sq.state, sq.next_state, clr);
    //  $monitor("y = %b", y);
        #10 x = 1;
        #10 x = 0;
        #10 x = 1;
    end
    
    always #5 clk = !clk;
endmodule

VCD/seq_detect_mealey.vcd
$date
	Sun Sep  4 21:24:57 2022
$end
$version
	Icarus Verilog
$end
$timescale
	1s
$end
$scope module tb_seq_detect $end
$var wire 1 ! y $end
$var wire 1 " state $end
$var wire 1 # next_state $end
$var reg 1 $ clk $end
$var reg 1 % clr $end
$var reg 1 & x $end
$scope module sq $end
$var wire 1 $ clk $end
$var wire 1 % clr $end
$var wire 1 & x $end
$var reg 2 ' next_state [1:0] $end
$var reg 2 ( state [1:0] $end
$var reg 1 ! y $end
$upscope $end
$upscope $end
$enddefinitions $end
#0
$dumpvars
b0 (
b0 '
x&
0%
0$
0#
0"
0!
$end
#5
1$
1%
#10
b10 '
0$
1&
#15
b10 (
1$
#20
1#
b1 '
1!
0$
0&
#25
1"
b1 (
1$
#30
0#
b10 '
0!
0$
1&
#35
0"
b10 (
1$
